Metadata-Version: 2.1
Name: poetry-demo-404rex
Version: 0.1.0
Summary: 
Author: Deven
Author-email: devendraa769@gmail.com
Requires-Python: >=3.8,<4.0
Classifier: Programming Language :: Python :: 3
Classifier: Programming Language :: Python :: 3.8
Classifier: Programming Language :: Python :: 3.9
Classifier: Programming Language :: Python :: 3.10
Classifier: Programming Language :: Python :: 3.11
Requires-Dist: starlette (>=0.28.0,<0.29.0)
Requires-Dist: uvicorn (>=0.22.0,<0.23.0)
